LICENSE
README.md
setup.cfg
setup.py
easy_explain/__init__.py
easy_explain.egg-info/PKG-INFO
easy_explain.egg-info/SOURCES.txt
easy_explain.egg-info/dependency_links.txt
easy_explain.egg-info/requires.txt
easy_explain.egg-info/top_level.txt
easy_explain/methods/__init__.py
easy_explain/methods/xai_base.py
easy_explain/methods/cam/__init__.py
easy_explain/methods/cam/cam.py
easy_explain/methods/lrp/__init__.py
easy_explain/methods/lrp/yolov8/__init__.py
easy_explain/methods/lrp/yolov8/common.py
easy_explain/methods/lrp/yolov8/initializers.py
easy_explain/methods/lrp/yolov8/inverter.py
easy_explain/methods/lrp/yolov8/inverter_util.py
easy_explain/methods/lrp/yolov8/rules.py
easy_explain/methods/lrp/yolov8/utils.py
easy_explain/methods/lrp/yolov8/yolo.py
easy_explain/methods/occlusion/__init__.py
easy_explain/methods/occlusion/occlusion.py
tests/__init__.py
tests/test_cam.py
tests/test_lrp.py
tests/test_occlusion.py