Metadata-Version: 2.1
Name: easy-explain
Version: 0.5.0
Summary: A library that helps to explain AI models in a really quick & easy way
Home-page: https://github.com/stavrostheocharis/stavrostheocharis
Download-URL: https://github.com/stavrostheocharis/easy_explain/archive/refs/tags/v0.5.0.tar.gz
Author: Stavros Theocharis
Author-email: stavrostheocharis@yahoo.gr
License: MIT
Keywords: explainable ai,xai,easy explain
Classifier: Development Status :: 4 - Beta
Classifier: Intended Audience :: Developers
Classifier: Topic :: Software Development :: Build Tools
Classifier: License :: OSI Approved :: MIT License
Classifier: Programming Language :: Python :: 3.9
Classifier: Programming Language :: Python :: 3.10
Classifier: Programming Language :: Python :: 3.11
License-File: LICENSE
Requires-Dist: backports.weakref
Requires-Dist: captum
Requires-Dist: matplotlib
Requires-Dist: opencv-python
Requires-Dist: Pillow
Requires-Dist: scikit-learn
Requires-Dist: scipy
Requires-Dist: torch
Requires-Dist: torchcam
Requires-Dist: torchvision
Requires-Dist: ultralytics
